nth_Bday/__init__.py
nth_Bday/nth_Bday.py
nth_Bday-0.0.1.dist-info/METADATA
nth_Bday-0.0.1.dist-info/WHEEL
nth_Bday-0.0.1.dist-info/top_level.txt
nth_Bday-0.0.1.dist-info/RECORD
