Metadata-Version: 2.1
Name: nth-Bday
Version: 0.0.1
Summary: Find the "n-th" working day of a month
Author: u77w41 (Ujjwal Chowdhury)
Author-email: <u77w41@gmail.com>
Keywords: python,date,Business Day,Working Day,Holiday,calender
Classifier: Development Status :: 1 - Planning
Classifier: Intended Audience :: Developers
Classifier: Programming Language :: Python :: 3
Classifier: Operating System :: Unix
Classifier: Operating System :: MacOS :: MacOS X
Classifier: Operating System :: Microsoft :: Windows
Requires-Dist: pandas
Requires-Dist: datetime
Requires-Dist: holidays
